zdpapi_file/__init__.py
zdpapi_file/directory.py
zdpapi_file/directory_test.py
zdpapi_file-0.1.0.dist-info/LICENSE
zdpapi_file-0.1.0.dist-info/WHEEL
zdpapi_file-0.1.0.dist-info/METADATA
zdpapi_file-0.1.0.dist-info/RECORD
